renault_api/__init__.py
renault_api/cli/__init__.py
renault_api/cli/__main__.py
renault_api/cli/charge/__init__.py
renault_api/cli/charge/commands.py
renault_api/cli/charge/control.py
renault_api/cli/charge/history.py
renault_api/cli/charge/schedule.py
renault_api/cli/helpers.py
renault_api/cli/hvac/__init__.py
renault_api/cli/hvac/commands.py
renault_api/cli/hvac/control.py
renault_api/cli/hvac/history.py
renault_api/cli/renault_account.py
renault_api/cli/renault_client.py
renault_api/cli/renault_settings.py
renault_api/cli/renault_vehicle.py
renault_api/const.py
renault_api/credential.py
renault_api/credential_store.py
renault_api/exceptions.py
renault_api/gigya/__init__.py
renault_api/gigya/exceptions.py
renault_api/gigya/models.py
renault_api/gigya/schemas.py
renault_api/helpers.py
renault_api/kamereon/__init__.py
renault_api/kamereon/enums.py
renault_api/kamereon/exceptions.py
renault_api/kamereon/helpers.py
renault_api/kamereon/models.py
renault_api/kamereon/schemas.py
renault_api/models.py
renault_api/py.typed
renault_api/renault_account.py
renault_api/renault_client.py
renault_api/renault_session.py
renault_api/renault_vehicle.py
renault_api-0.5.2.dist-info/METADATA
renault_api-0.5.2.dist-info/WHEEL
renault_api-0.5.2.dist-info/entry_points.txt
renault_api-0.5.2.dist-info/licenses/LICENSE.rst
renault_api-0.5.2.dist-info/RECORD
