Metadata-Version: 2.4
Name: renault-api
Version: 0.5.2
Summary: Renault API
License: MIT
License-File: LICENSE.rst
Author: epenet
Requires-Python: >=3.10,<4.0
Classifier: License :: OSI Approved :: MIT License
Classifier: Programming Language :: Python :: 3
Classifier: Programming Language :: Python :: 3.10
Classifier: Programming Language :: Python :: 3.11
Classifier: Programming Language :: Python :: 3.12
Classifier: Programming Language :: Python :: 3.13
Classifier: Programming Language :: Python :: 3.14
Provides-Extra: cli
Requires-Dist: PyJWT (>=2.8.0)
Requires-Dist: aiohttp (>=3.9.5)
Requires-Dist: cffi (>=1.17.0)
Requires-Dist: click (>=8.0.1) ; extra == "cli"
Requires-Dist: cryptography (>=44.0.0)
Requires-Dist: dateparser (>=1.0.0) ; extra == "cli"
Requires-Dist: marshmallow-dataclass (>=8.2.0)
Requires-Dist: tabulate (>=0.8.7) ; extra == "cli"
Project-URL: Changelog, https://github.com/hacf-fr/renault-api/releases
Project-URL: Documentation, https://renault-api.readthedocs.io
Project-URL: Homepage, https://github.com/hacf-fr/renault-api
Project-URL: Repository, https://github.com/hacf-fr/renault-api
